nbparameterise/__init__.py
nbparameterise/code.py
nbparameterise/code_drivers/__init__.py
nbparameterise/code_drivers/python.py
nbparameterise-0.6.1.dist-info/LICENSE
nbparameterise-0.6.1.dist-info/WHEEL
nbparameterise-0.6.1.dist-info/METADATA
nbparameterise-0.6.1.dist-info/RECORD
