Metadata-Version: 2.1
Name: nbparameterise
Version: 0.6.1
Summary: Re-run a notebook substituting input parameters in the first cell.
Author-email: Thomas Kluyver <thomas@kluyver.me.uk>
Requires-Python: >=3.8
Classifier: License :: OSI Approved :: MIT License
Classifier: Framework :: Jupyter
Requires-Dist: nbformat
Requires-Dist: astcheck >=0.3
Project-URL: Source, https://github.com/takluyver/nbparameterise
